kafka_bluesky_live/__init__.py
kafka_bluesky_live/live_view.py
kafka_bluesky_live/utils.py
kafka_bluesky_live/configs/__init__.py
kafka_bluesky_live/configs/main_window_config.py
kafka_bluesky_live/scripts/__init__.py
kafka_bluesky_live/scripts/live_view_caller.py
kafka_bluesky_live/ui/__init__.py
kafka_bluesky_live/ui/main_window_ui.py
kafka_bluesky_live/ui/icons/__init__.py
kafka_bluesky_live/ui/icons/background.jpg
kafka_bluesky_live/ui/icons/cnpem.png
kafka_bluesky_live/ui/icons/lnls-sirius.png
kafka_bluesky_live/widgets/__init__.py
kafka_bluesky_live/widgets/live_view_tab.py
kafka_bluesky_live/widgets/thread_safe_plot.py
kafka_bluesky_live/widgets/worker_thread.py
kafka_bluesky_live-0.0.1.dist-info/METADATA
kafka_bluesky_live-0.0.1.dist-info/WHEEL
kafka_bluesky_live-0.0.1.dist-info/entry_points.txt
kafka_bluesky_live-0.0.1.dist-info/top_level.txt
kafka_bluesky_live-0.0.1.dist-info/RECORD
