Metadata-Version: 2.1
Name: kafka-bluesky-live
Version: 0.0.1
Summary: This is a live view for data produced by Bluesky in the so called Documents and streamed via Kafka.
Home-page: https://gitlab.cnpem.br/SOL/bluesky/kafka-bluesky-live
Author: Hugo Campos
Author-email: hugo.campos@lnls.br
Classifier: Development Status :: 1 - Planning
Classifier: Environment :: Console
Classifier: Intended Audience :: Developers
Classifier: License :: OSI Approved :: GNU General Public License v3 or later (GPLv3+)
Classifier: Operating System :: OS Independent
Classifier: Programming Language :: Python :: 3
Requires-Dist: wheel
Requires-Dist: pyqt5
Requires-Dist: silx
Requires-Dist: numpy
Requires-Dist: python-dateutil
Requires-Dist: kafka-python
